<Root>
<styles>
    <include src="file://{resources}/styles/main.scss" />
    <include src="file://{resources}/styles/components/steam-input.scss" />
    <include src="file://{resources}/styles/pages/archipelago/base.scss" />
    <include src="file://{resources}/styles/pages/archipelago/map-select.scss" />
</styles>

<scripts>
    <include src="file://{scripts}/util/archipelago-api.ts" />
    <include src="file://{scripts}/util/archipelago-logic.ts" />
    <include src="file://{scripts}/util/archipelago-sync.ts" />
    <include src="file://{scripts}/pages/archipelago/map-select.ts" />
</scripts>

    <Panel class="archipelago__page mainmenu__page mainmenu" onload="ArchipelagoMapSelect.onLoad()">
        <Panel id="MainBox" class="main_box" style="flow-children: none;">
            
            <!-- NOT CONNECTED STATE -->
            <Panel id="NotConnectedOverlay" class="not_connected_overlay hide">
                <Image src="file://{images}/archipelago/warning_orange_v3.png" class="warning_icon" scaling="stretch-to-fit-preserve-aspect" />
                <Label class="warning_title" text="#Archipelago_Status_NotConnected" />
                <Button class="warning_button" onactivate="ArchipelagoMapSelect.toggleConsole()">
                    <Label text="#Archipelago_Console_Title" />
                </Button>
            </Panel>

            <Panel id="ConnectedContent" style="width: 100%; height: 100%; flow-children: down;">
                <Panel id="ColumnsWrapper" class="columns_wrapper">
                <!-- LEFT COLUMN -->
                <Panel id="LeftList" class="left_list_container">
                    <Panel id="LeftListInner" class="left_list_inner" />
                </Panel>

                <!-- RIGHT PREVIEW -->
                <Panel id="RightPreview" class="right_preview">
                    <Image
                        id="PreviewImage"
                        src=""
                        class="preview_image"
                        scaling="stretch-to-cover-preserve-aspect" />
                </Panel>
            </Panel>

            <!-- FULL WIDTH CONTROL BAR -->
            <Panel id="FullWidthFooter" class="preview_bottom_row">
                
                <!-- ALIGNMENT SPACER -->
                <Panel id="FooterAlignmentSpacer" class="footer_alignment_spacer">
                    <Panel class="help_button_wrapper">
                        <Panel class="button_with_tooltip">
                            <Panel id="ManualHelpTooltip" class="manual_tooltip">
                                <Label text="#Archipelago_Help_Tooltip" />
                                <Panel class="manual_tooltip_arrow" />
                            </Panel>
                            <Button id="HelpButton"
                                    class="help_button"
                                    onmouseover="$( '#ManualHelpTooltip' ).AddClass('visible'); $.PlaySoundEvent('UIPanorama.P2CE.MenuFocus')"
                                    onmouseout="$( '#ManualHelpTooltip' ).RemoveClass('visible')"
                                    onactivate="$.PlaySoundEvent('UIPanorama.P2CE.MenuAccept'); ArchipelagoMapSelect.showHelp()">
                                <Image class="help_button_icon" src="file://{images}/learn.svg" />
                            </Button>
                        </Panel>
                    </Panel>
                </Panel>

                <!-- CONTENT STARTING UNDER PICTURE -->
                <Panel id="FooterContent" class="footer_content">
                    <Panel id="MapInfoContainer" class="map_info_container">
                        <!-- CHAPTER/TITLE LABEL -->
                        <Panel id="TitleColumn" class="title_column">
                            <Label id="MapSubtitleLabel" class="map_subtitle_label" text="" />
                        </Panel>

                        <!-- CHECKS -->
                        <Panel id="ChecksColumn" class="info_column">
                            <Label id="ChecksHeader" class="info_header" text="#Archipelago_Map_Checks" style="visibility:collapse;" />
                            <Label id="MapStatusIconsPreview" class="map_status_preview_label" text="" html="true" />
                        </Panel>

                        <!-- REQUIREMENTS -->
                        <Panel id="RequirementsColumn" class="info_column">
                            <Label id="MissingItemsHeader" class="info_header" text="#Archipelago_Map_MissingItems" style="visibility:collapse;" />
                            <Label id="MapSubtitleLabel_Secondary" class="map_subtitle_label" text="" html="true" />
                        </Panel>
                    </Panel>

                    <!-- PUSHES PLAY BUTTON TO THE RIGHT -->
                    <Panel id="PlayButtonSpacer" class="footer_spacer" />

                    <Button id="PlayButton"
                            style="visibility:collapse;"
                            class="play_button"
                            onmouseover="$.PlaySoundEvent('UIPanorama.P2CE.MenuFocus')"
                            onactivate="$.PlaySoundEvent('UIPanorama.P2CE.MenuAccept'); ArchipelagoMapSelect.playSelectedMap()">
                        <Label class="play_button_text" text="#MainMenu_Navigation_Play" />
                    </Button>
                </Panel>
            </Panel>

            </Panel>
        </Panel>
    </Panel>

    
</Root>